odoo/addons/account_invoice_report_grouped_by_picking/README.rst
odoo/addons/account_invoice_report_grouped_by_picking/__init__.py
odoo/addons/account_invoice_report_grouped_by_picking/__manifest__.py
odoo/addons/account_invoice_report_grouped_by_picking/i18n/account_invoice_report_grouped_by_picking.pot
odoo/addons/account_invoice_report_grouped_by_picking/i18n/de.po
odoo/addons/account_invoice_report_grouped_by_picking/i18n/es.po
odoo/addons/account_invoice_report_grouped_by_picking/i18n/fr_FR.po
odoo/addons/account_invoice_report_grouped_by_picking/i18n/it.po
odoo/addons/account_invoice_report_grouped_by_picking/i18n/pt.po
odoo/addons/account_invoice_report_grouped_by_picking/i18n/pt_BR.po
odoo/addons/account_invoice_report_grouped_by_picking/models/__init__.py
odoo/addons/account_invoice_report_grouped_by_picking/models/account_move.py
odoo/addons/account_invoice_report_grouped_by_picking/readme/CONTRIBUTORS.md
odoo/addons/account_invoice_report_grouped_by_picking/readme/CREDITS.md
odoo/addons/account_invoice_report_grouped_by_picking/readme/DESCRIPTION.md
odoo/addons/account_invoice_report_grouped_by_picking/readme/USAGE.md
odoo/addons/account_invoice_report_grouped_by_picking/static/description/icon.png
odoo/addons/account_invoice_report_grouped_by_picking/static/description/index.html
odoo/addons/account_invoice_report_grouped_by_picking/tests/__init__.py
odoo/addons/account_invoice_report_grouped_by_picking/tests/test_account_invoice_group_picking.py
odoo/addons/account_invoice_report_grouped_by_picking/views/report_invoice.xml
odoo_addon_account_invoice_report_grouped_by_picking-18.0.1.0.1.dist-info/METADATA
odoo_addon_account_invoice_report_grouped_by_picking-18.0.1.0.1.dist-info/WHEEL
odoo_addon_account_invoice_report_grouped_by_picking-18.0.1.0.1.dist-info/top_level.txt
odoo_addon_account_invoice_report_grouped_by_picking-18.0.1.0.1.dist-info/RECORD
