Metadata-Version: 2.1
Name: odoo-addon-account_invoice_report_grouped_by_picking
Version: 18.0.1.0.1
Requires-Python: >=3.10
Requires-Dist: odoo-addon-sale_stock_picking_invoice_link==18.0.*
Requires-Dist: odoo==18.0.*
Summary: Print invoice lines grouped by picking
Home-page: https://github.com/OCA/account-invoice-reporting
License: AGPL-3
Author: Tecnativa, Odoo Community Association (OCA)
Author-email: support@odoo-community.org
Classifier: Programming Language :: Python
Classifier: Framework :: Odoo
Classifier: Framework :: Odoo :: 18.0
Classifier: License :: OSI Approved :: GNU Affero General Public License v3
